objifier/__init__.py
objifier/build.py
objifier/data_loader.py
objifier/log.py
objifier/main.py
objifier/model.py
objifier/normalize.py
objifier/train.py
objifier/version.py
objifier/visualize.py
objifier/efficientnet/__init__.py
objifier/efficientnet/model.py
objifier/efficientnet/utils.py
objifier-0.1.1.dist-info/LICENSE
objifier-0.1.1.dist-info/METADATA
objifier-0.1.1.dist-info/WHEEL
objifier-0.1.1.dist-info/top_level.txt
objifier-0.1.1.dist-info/RECORD
