Metadata-Version: 2.1
Name: objifier
Version: 0.1.1
Summary: Object Classifier
Home-page: https://github.com/1chimaruGin/object-classifier
Author: kyitharhein
Author-email: kyitharhein18@gmail.com
License: UNKNOWN
Download-URL: https://github.com/1chimaruGin/object-classifier/archive/v_0.1.1.tar.gz
Platform: UNKNOWN
Classifier: Development Status :: 3 - Alpha
Classifier: Intended Audience :: Education
Classifier: Intended Audience :: Science/Research
Classifier: License :: OSI Approved :: Apache Software License
Classifier: Programming Language :: Python :: 3.6
Classifier: Programming Language :: Python :: 3.7
Classifier: Programming Language :: Python :: 3.8
Classifier: Topic :: Scientific/Engineering
Classifier: Topic :: Scientific/Engineering :: Artificial Intelligence
Classifier: Topic :: Software Development
Classifier: Topic :: Software Development :: Libraries
Classifier: Topic :: Software Development :: Libraries :: Python Modules
Requires-Python: >=3.6
Requires-Dist: torch (>=1.5.1)
Requires-Dist: torchvision (>=0.6.1)
Requires-Dist: matplotlib
Requires-Dist: numpy
Requires-Dist: argparse (==1.4.0)
Requires-Dist: tqdm
Requires-Dist: pyyaml
